Metadata-Version: 2.1
Name: cryoloBM
Version: 1.5.4
Summary: Boxmanager to create training data for crYOLO
Home-page: 
Author: Thorsten Wagner
Author-email: thorsten.wagner@mpi-dortmund.mpg.de
License: MIT
Requires-Python: >3.4.0
License-File: LICENSE
